funannotate/__init__.py
funannotate/__version__.py
funannotate/annotate.py
funannotate/check.py
funannotate/clean.py
funannotate/compare.py
funannotate/database.py
funannotate/downloads.json
funannotate/fix.py
funannotate/funannotate.py
funannotate/interlap.py
funannotate/iprscan.py
funannotate/library.py
funannotate/mask.py
funannotate/outgroups.py
funannotate/predict.py
funannotate/remote.py
funannotate/resources.py
funannotate/setupDB.py
funannotate/sort.py
funannotate/species.py
funannotate/stackedBarGraph.py
funannotate/test.py
funannotate/train.py
funannotate/update.py
funannotate/aux_scripts/augustus_parallel.py
funannotate/aux_scripts/enrichment_parallel.py
funannotate/aux_scripts/fasta2agp.py
funannotate/aux_scripts/filterGenemark.pl
funannotate/aux_scripts/filterIntronsFindStrand.pl
funannotate/aux_scripts/funannotate-BUSCO2-py2.py
funannotate/aux_scripts/funannotate-BUSCO2.py
funannotate/aux_scripts/funannotate-p2g.py
funannotate/aux_scripts/funannotate-runEVM.py
funannotate/aux_scripts/genemark_gtf2gff3.pl
funannotate/aux_scripts/getEggNog.sh
funannotate/aux_scripts/hmmer_parallel.py
funannotate/aux_scripts/iprscan-local.py
funannotate/aux_scripts/iprscan2annotations.py
funannotate/aux_scripts/pal2nal.pl
funannotate/aux_scripts/phobius-multiproc.py
funannotate/aux_scripts/phobius-remote.pl
funannotate/aux_scripts/runIPRscan.py
funannotate/aux_scripts/sam2bam.sh
funannotate/aux_scripts/tbl2asn_parallel.py
funannotate/aux_scripts/trinity.py
funannotate/aux_scripts/trnascan2gff3.pl
funannotate/aux_scripts/xmlcombine.py
funannotate/config/EOG092C0B3U.prfl
funannotate/config/TruSeq3-PE.fa
funannotate/config/TruSeq3-SE.fa
funannotate/config/busco_test.fa
funannotate/config/codeml.config
funannotate/config/extrinsic.E.XNT.RM.cfg
funannotate/config/smcogs.txt
funannotate/config/test.sbt
funannotate/config/tf_interpro.txt
funannotate/html_template/css/bootstrap.min.css
funannotate/html_template/css/starter-template.css
funannotate-1.8.17.dist-info/LICENSE.md
funannotate-1.8.17.dist-info/METADATA
funannotate-1.8.17.dist-info/WHEEL
funannotate-1.8.17.dist-info/entry_points.txt
funannotate-1.8.17.dist-info/top_level.txt
funannotate-1.8.17.dist-info/RECORD
