Metadata-Version: 2.1
Name: funannotate
Version: 1.8.17
Summary: funannotate: eukaryotic genome annotation pipeline
Home-page: https://github.com/nextgenusfs/funannotate
Author: Jon Palmer
Author-email: nextgenusfs@gmail.com
License: BSD-2
Classifier: Development Status :: 4 - Beta
Classifier: License :: OSI Approved :: BSD License
Classifier: Programming Language :: Python
Classifier: Operating System :: Unix
Classifier: Intended Audience :: Science/Research
Classifier: Topic :: Scientific/Engineering :: Bio-Informatics
Requires-Python: >=3.6.0, <3.10
License-File: LICENSE.md
Requires-Dist: biopython <1.80
Requires-Dist: goatools
Requires-Dist: seaborn
Requires-Dist: psutil
Requires-Dist: pandas
Requires-Dist: matplotlib
Requires-Dist: natsort
Requires-Dist: numpy
Requires-Dist: requests
Requires-Dist: scikit-learn
Requires-Dist: scipy
Requires-Dist: distro
